filthypasswordgenerator/__init__.py
filthypasswordgenerator/__main__.py
filthypasswordgenerator/pwgenerator.py
filthypasswordgenerator/data/__init__.py
filthypasswordgenerator/data/english.py
filthypasswordgenerator/data/makeenglish.py
filthypasswordgenerator-1.4.dist-info/LICENSE
filthypasswordgenerator-1.4.dist-info/METADATA
filthypasswordgenerator-1.4.dist-info/WHEEL
filthypasswordgenerator-1.4.dist-info/entry_points.txt
filthypasswordgenerator-1.4.dist-info/top_level.txt
filthypasswordgenerator-1.4.dist-info/RECORD
