Metadata-Version: 2.1
Name: filthypasswordgenerator
Version: 1.4
Summary: Passwords that make humans hard
Home-page: https://github.com/banreaxe/filthy-password-generator-py
Author: Mark
Author-email: banreaxe@gmail.com
License: MIT
Platform: UNKNOWN
Classifier: Topic :: Security
Classifier: License :: OSI Approved :: MIT License
Classifier: Operating System :: MacOS
Classifier: Operating System :: POSIX :: Linux
Classifier: Natural Language :: English
Classifier: Programming Language :: Python :: 2.7
Classifier: Programming Language :: Python :: 3
Classifier: Programming Language :: Python
Classifier: Development Status :: 5 - Production/Stable
Requires-Dist: argparse
